caspian/__init__.py
caspian/backend/__init__.py
caspian/backend/columnar.py
caspian/cli.py
caspian/query/__init__.py
caspian/query/api.py
caspian/synthesis/__init__.py
caspian/synthesis/bag.py
caspian/timestamp.py
caspian/warehouse/__init__.py
caspian-0.2.0.dist-info/LICENSE
caspian-0.2.0.dist-info/METADATA
caspian-0.2.0.dist-info/WHEEL
caspian-0.2.0.dist-info/entry_points.txt
caspian-0.2.0.dist-info/RECORD
