Metadata-Version: 2.1
Name: caspian
Version: 0.2.0
Summary: 
Author: Kevin Wierman
Author-email: kwierman@gmail.com
Requires-Python: >=3.11,<4.0
Classifier: Programming Language :: Python :: 3
Classifier: Programming Language :: Python :: 3.11
Classifier: Programming Language :: Python :: 3.12
Classifier: Programming Language :: Python :: 3.13
Requires-Dist: dask (>=2024.7.0,<2025.0.0)
Requires-Dist: distributed (>=2024.7.0,<2025.0.0)
Requires-Dist: fastapi (>=0.111.0,<0.112.0)
Requires-Dist: sqlalchemy (>=2.0.31,<3.0.0)
Requires-Dist: uvicorn (>=0.32.1,<0.33.0)
